odoo/addons/edi_voxel_oca/README.rst
odoo/addons/edi_voxel_oca/__init__.py
odoo/addons/edi_voxel_oca/__manifest__.py
odoo/addons/edi_voxel_oca/data/data_voxel_uom.xml
odoo/addons/edi_voxel_oca/data/queue_job_channel_data.xml
odoo/addons/edi_voxel_oca/i18n/edi_voxel.pot
odoo/addons/edi_voxel_oca/i18n/edi_voxel_oca.pot
odoo/addons/edi_voxel_oca/i18n/es.po
odoo/addons/edi_voxel_oca/i18n/it.po
odoo/addons/edi_voxel_oca/models/__init__.py
odoo/addons/edi_voxel_oca/models/account.py
odoo/addons/edi_voxel_oca/models/queue_job.py
odoo/addons/edi_voxel_oca/models/res_company.py
odoo/addons/edi_voxel_oca/models/res_config_settings.py
odoo/addons/edi_voxel_oca/models/res_partner.py
odoo/addons/edi_voxel_oca/models/uom_uom.py
odoo/addons/edi_voxel_oca/models/voxel_login.py
odoo/addons/edi_voxel_oca/models/voxel_mixin.py
odoo/addons/edi_voxel_oca/readme/CONTRIBUTORS.md
odoo/addons/edi_voxel_oca/readme/DESCRIPTION.md
odoo/addons/edi_voxel_oca/security/ir.model.access.csv
odoo/addons/edi_voxel_oca/security/voxel_security.xml
odoo/addons/edi_voxel_oca/static/description/icon.png
odoo/addons/edi_voxel_oca/static/description/index.html
odoo/addons/edi_voxel_oca/views/account_tax_views.xml
odoo/addons/edi_voxel_oca/views/product_uom_views.xml
odoo/addons/edi_voxel_oca/views/res_company_view.xml
odoo/addons/edi_voxel_oca/views/res_config_settings_views.xml
odoo/addons/edi_voxel_oca/views/res_partner_views.xml
odoo/addons/edi_voxel_oca/views/template_voxel_report.xml
odoo/addons/edi_voxel_oca/views/voxel_login_views.xml
odoo_addon_edi_voxel_oca-18.0.1.0.0.10.dist-info/METADATA
odoo_addon_edi_voxel_oca-18.0.1.0.0.10.dist-info/WHEEL
odoo_addon_edi_voxel_oca-18.0.1.0.0.10.dist-info/top_level.txt
odoo_addon_edi_voxel_oca-18.0.1.0.0.10.dist-info/RECORD
