Metadata-Version: 2.1
Name: odoo-addon-edi_voxel_oca
Version: 18.0.1.0.0.10
Requires-Python: >=3.10
Requires-Dist: odoo-addon-base_iso3166==18.0.*
Requires-Dist: odoo-addon-product_customerinfo==18.0.*
Requires-Dist: odoo-addon-queue_job==18.0.*
Requires-Dist: odoo-addon-report_xml==18.0.*
Requires-Dist: odoo==18.0.*
Summary: Base module for connecting with Voxel
Home-page: https://github.com/OCA/edi-voxel
License: AGPL-3
Author: Tecnativa, Odoo Community Association (OCA)
Author-email: support@odoo-community.org
Classifier: Programming Language :: Python
Classifier: Framework :: Odoo
Classifier: Framework :: Odoo :: 18.0
Classifier: License :: OSI Approved :: GNU Affero General Public License v3
Classifier: Development Status :: 5 - Production/Stable
